ocellaris/__init__.py
ocellaris/__main__.py
ocellaris/input_file_schema.yml
ocellaris/run.py
ocellaris/verify_environment.py
ocellaris/cpp/__init__.py
ocellaris/cpp/gradient_reconstruction.h
ocellaris/cpp/linear_convection.h
ocellaris/cpp/slope_limiter/hierarchical_taylor.h
ocellaris/cpp/slope_limiter/limiter_common.h
ocellaris/cpp/slope_limiter/measure_local_maxima.h
ocellaris/cpp/slope_limiter/naive_nodal.h
ocellaris/probes/__init__.py
ocellaris/probes/iso_surface.py
ocellaris/probes/line_probe.py
ocellaris/probes/plane_probe.py
ocellaris/probes/point_probe.py
ocellaris/probes/free_surface_locator/__init__.py
ocellaris/probes/free_surface_locator/vof_dg0_surface_locator.py
ocellaris/simulation/__init__.py
ocellaris/simulation/hooks.py
ocellaris/simulation/input.py
ocellaris/simulation/io.py
ocellaris/simulation/log.py
ocellaris/simulation/reporting.py
ocellaris/simulation/setup.py
ocellaris/simulation/simulation.py
ocellaris/simulation/solution_properties.py
ocellaris/simulation/io_impl/__init__.py
ocellaris/simulation/io_impl/debug.py
ocellaris/simulation/io_impl/legacy_vtk.py
ocellaris/simulation/io_impl/restart_h5.py
ocellaris/simulation/io_impl/xdmf.py
ocellaris/solver_parts/__init__.py
ocellaris/solver_parts/ale.py
ocellaris/solver_parts/bdm.py
ocellaris/solver_parts/forcing_zone.py
ocellaris/solver_parts/hydrostatic.py
ocellaris/solver_parts/penalty.py
ocellaris/solver_parts/runge_kutta.py
ocellaris/solver_parts/timestepping.py
ocellaris/solver_parts/boundary_conditions/__init__.py
ocellaris/solver_parts/boundary_conditions/boundary_region.py
ocellaris/solver_parts/boundary_conditions/decomposed.py
ocellaris/solver_parts/boundary_conditions/dirichlet.py
ocellaris/solver_parts/boundary_conditions/dof_marker.py
ocellaris/solver_parts/boundary_conditions/neumann.py
ocellaris/solver_parts/boundary_conditions/outlet.py
ocellaris/solver_parts/boundary_conditions/robin.py
ocellaris/solver_parts/boundary_conditions/slip_length.py
ocellaris-2019.1.0.dist-info/AUTHORS
ocellaris-2019.1.0.dist-info/LICENSE
ocellaris-2019.1.0.dist-info/METADATA
ocellaris-2019.1.0.dist-info/WHEEL
ocellaris-2019.1.0.dist-info/entry_points.txt
ocellaris-2019.1.0.dist-info/top_level.txt
ocellaris-2019.1.0.dist-info/RECORD
