Metadata-Version: 2.1
Name: ocellaris
Version: 2019.1.0
Summary: A discontinuous Galerkin FEM solver for multiphase free surface flows
Home-page: https://www.ocellaris.org/
Author: Tormod Landet and the Ocellaris project contributors
Author-email: tormod@landet.net
License: Apache 2.0
Keywords: fem fenics cfd dg navier-stokes multi-phase flow
Platform: UNKNOWN
Classifier: Development Status :: 5 - Production/Stable
Classifier: Intended Audience :: Science/Research
Classifier: Topic :: Scientific/Engineering :: Mathematics
Classifier: Topic :: Scientific/Engineering :: Physics
Classifier: License :: OSI Approved :: Apache Software License
Classifier: Programming Language :: Python :: 3
Classifier: Programming Language :: C++
Requires-Dist: PyYAML (>=5.1)
Requires-Dist: h5py
Requires-Dist: numpy
Requires-Dist: matplotlib
Requires-Dist: meshio (>=2.0.0)
Requires-Dist: raschii (>=1.0.2)
Requires-Dist: yschema (>=1.0.2)
Requires-Dist: fenics-dolfin (<2019.2,>=2018.1.0.dev0)
